django_dynamic_choices-1.1.0.dist-info/WHEEL
django_dynamic_choices-1.1.0.dist-info/RECORD
django_dynamic_choices-1.1.0.dist-info/metadata.json
django_dynamic_choices-1.1.0.dist-info/DESCRIPTION.rst
django_dynamic_choices-1.1.0.dist-info/LICENSE.txt
django_dynamic_choices-1.1.0.dist-info/top_level.txt
django_dynamic_choices-1.1.0.dist-info/METADATA
dynamic_choices/models.py
dynamic_choices/admin.py
dynamic_choices/compat.py
dynamic_choices/__init__.py
dynamic_choices/static/js/dynamic-choices.js
dynamic_choices/static/js/dynamic-choices-admin.js
dynamic_choices/templates/admin/dynamic_choices/change_form.html
dynamic_choices/forms/fields.py
dynamic_choices/forms/__init__.py
dynamic_choices/db/models.py
dynamic_choices/db/query.py
dynamic_choices/db/__init__.py
