Metadata-Version: 2.0
Name: django-dynamic-choices
Version: 1.1.0
Summary: Django admin fk and m2m dynamic choices by providing callback support
Home-page: https://github.com/charettes/django-dynamic-choices
Author: Simon Charette
Author-email: charette.s+django-dynamic-choices@gmail.com
License: MIT
Keywords: django admin choices dynamic
Platform: UNKNOWN
Classifier: Development Status :: 5 - Production/Stable
Classifier: Environment :: Web Environment
Classifier: Framework :: Django
Classifier: Intended Audience :: Developers
Classifier: License :: OSI Approved :: MIT License
Classifier: Operating System :: OS Independent
Classifier: Programming Language :: Python
Classifier: Programming Language :: Python :: 2
Classifier: Programming Language :: Python :: 2.6
Classifier: Programming Language :: Python :: 2.7
Classifier: Topic :: Internet :: WWW/HTTP
Classifier: Topic :: Internet :: WWW/HTTP :: Dynamic Content
Classifier: Topic :: Internet :: WWW/HTTP :: WSGI
Classifier: Topic :: Software Development :: Libraries :: Application Frameworks
Classifier: Topic :: Software Development :: Libraries :: Python Modules
Requires-Dist: Django (>=1.4,<1.8)
